{
	"UdonSharp.Examples.Utilities.MasterToggleObject.Start()": {
		"methodName": "_start",
		"parameters": null
	},
	"UdonSharp.Examples.Utilities.MasterToggleObject.OnOwnershipRequest(VRC.SDKBase.VRCPlayerApi, VRC.SDKBase.VRCPlayerApi)": {
		"methodName": "_onOwnershipRequest",
		"parameters": [
			"onOwnershipRequestRequester",
			"onOwnershipRequestNewOwner"
		]
	},
	"UdonSharp.Examples.Utilities.MasterToggleObject.OnDeserialization()": {
		"methodName": "_onDeserialization",
		"parameters": null
	},
	"UdonSharp.Examples.Utilities.MasterToggleObject.Interact()": {
		"methodName": "_interact",
		"parameters": null
	},
	"Miner28.UdonUtils.Network.NetworkManager.Start()": {
		"methodName": "_start",
		"parameters": null
	},
	"Miner28.UdonUtils.Network.NetworkManager.OnPlayerJoined(VRC.SDKBase.VRCPlayerApi)": {
		"methodName": "_onPlayerJoined",
		"parameters": [
			"onPlayerJoinedPlayer"
		]
	},
	"Miner28.UdonUtils.Network.NetworkManager.OnPlayerRestored(VRC.SDKBase.VRCPlayerApi)": {
		"methodName": "_onPlayerRestored",
		"parameters": [
			"onPlayerRestoredPlayer"
		]
	},
	"Miner28.UdonUtils.Network.NetworkManager.BackwardsRegister(Miner28.UdonUtils.Network.NetworkedEventCaller)": {
		"methodName": "__0_BackwardsRegister",
		"parameters": [
			"__0_caller__param"
		]
	},
	"Miner28.UdonUtils.Network.NetworkManager.ToggleNetworking(bool, bool)": {
		"methodName": "__0_ToggleNetworking",
		"parameters": [
			"__0_state__param",
			"__0_voidEvents__param"
		]
	},
	"Miner28.UdonUtils.Network.NetworkManager.HandlePaused(VRC.SDKBase.VRCPlayerApi, byte[])": {
		"methodName": "__0_HandlePaused",
		"parameters": [
			"__0_sender__param",
			"__0_data__param"
		]
	},
	"Miner28.UdonUtils.Network.NetworkManager._HandleNetworkResumed()": {
		"methodName": "_HandleNetworkResumed",
		"parameters": null
	},
	"Miner28.UdonUtils.Network.NetworkManager.Log(object)": {
		"methodName": "__0_Log",
		"parameters": [
			"__0_log__param"
		]
	},
	"Miner28.UdonUtils.Network.NetworkManager.Log(string)": {
		"methodName": "__1_Log",
		"parameters": [
			"__1_log__param"
		]
	},
	"Miner28.UdonUtils.Network.NetworkManager.OnCallerAssigned()": {
		"methodName": "OnCallerAssigned",
		"parameters": null
	},
	"Dialogue_Statue_1.Start()": {
		"methodName": "_start",
		"parameters": null
	},
	"Dialogue_Skull_1.Start()": {
		"methodName": "_start",
		"parameters": null
	},
	"Miner28.UdonUtils.Network.NetworkInterface.SendMethodNetworked(string, SyncTarget, params VRC.SDK3.Data.DataToken[])": {
		"methodName": "__0_SendMethodNetworked",
		"parameters": [
			"__0_methodName__param",
			"__0_target__param",
			"__0_paramTokens__param"
		]
	},
	"Miner28.UdonUtils.Network.NetworkInterface.SendMethodNetworked(string, VRC.SDKBase.VRCPlayerApi, params VRC.SDK3.Data.DataToken[])": {
		"methodName": "__1_SendMethodNetworked",
		"parameters": [
			"__1_methodName__param",
			"__1_target__param",
			"__1_paramTokens__param"
		]
	},
	"Miner28.UdonUtils.Network.NetworkInterface.SendMethodNetworked(string, SyncChannel, params VRC.SDK3.Data.DataToken[])": {
		"methodName": "__2_SendMethodNetworked",
		"parameters": [
			"__2_methodName__param",
			"__0_channel__param",
			"__2_paramTokens__param"
		]
	},
	"Miner28.UdonUtils.Network.NetworkInterface.SetupInterface()": {
		"methodName": "SetupInterface",
		"parameters": null
	},
	"Miner28.UdonUtils.Network.NetworkInterface.OnCallerAssigned()": {
		"methodName": "OnCallerAssigned",
		"parameters": null
	},
	"UseTeleporter.Start()": {
		"methodName": "_start",
		"parameters": null
	},
	"UseTeleporter.FindVRCWorldObjectInScene()": {
		"methodName": "FindVRCWorldObjectInScene",
		"parameters": null
	},
	"UseTeleporter.Interact()": {
		"methodName": "_interact",
		"parameters": null
	},
	"SkeletonHead.Start()": {
		"methodName": "_start",
		"parameters": null
	},
	"SkeletonHead.Bless()": {
		"methodName": "Bless",
		"parameters": null
	},
	"SkeletonHead.Update()": {
		"methodName": "_update",
		"parameters": null
	},
	"QuestManager.FindVRCWorldObjectInScene()": {
		"methodName": "FindVRCWorldObjectInScene",
		"parameters": null
	},
	"QuestManager.TeleportTo(UnityEngine.Transform)": {
		"methodName": "__0_TeleportTo",
		"parameters": [
			"__0_transform__param"
		]
	},
	"QuestManager.OnTrigger(string, float)": {
		"methodName": "__0_OnTrigger",
		"parameters": [
			"__0_token__param",
			"__0_delay__param"
		]
	},
	"QuestManager.TP_TO_JAIL()": {
		"methodName": "TP_TO_JAIL",
		"parameters": null
	},
	"QuestManager.WALL_SMASH()": {
		"methodName": "WALL_SMASH",
		"parameters": null
	},
	"QuestManager.DeactivateExpiredParticleSystemExplosionEffect()": {
		"methodName": "DeactivateExpiredParticleSystemExplosionEffect",
		"parameters": null
	},
	"QuestManager.OnSpellBallExploded()": {
		"methodName": "OnSpellBallExploded",
		"parameters": null
	},
	"QuestManager.StopRightThere()": {
		"methodName": "StopRightThere",
		"parameters": null
	},
	"QuestManager.FreePlayer()": {
		"methodName": "FreePlayer",
		"parameters": null
	},
	"QuestManager.JailWizardLeave()": {
		"methodName": "JailWizardLeave",
		"parameters": null
	},
	"QuestManager.TestIfJailWizardReachedExit()": {
		"methodName": "TestIfJailWizardReachedExit",
		"parameters": null
	},
	"QuestManager.CleanupJailQuestObjects()": {
		"methodName": "CleanupJailQuestObjects",
		"parameters": null
	},
	"QuestManager.OnStartSkullQuest()": {
		"methodName": "OnStartSkullQuest",
		"parameters": null
	},
	"QuestManager.OnHeadlessSkeletonTriggered()": {
		"methodName": "OnHeadlessSkeletonTriggered",
		"parameters": null
	},
	"QuestManager.AfterEntranceEffectFinished()": {
		"methodName": "AfterEntranceEffectFinished",
		"parameters": null
	},
	"QuestManager.BeginReturnSkull()": {
		"methodName": "BeginReturnSkull",
		"parameters": null
	},
	"QuestManager.OnSkullReturned()": {
		"methodName": "OnSkullReturned",
		"parameters": null
	},
	"QuestManager.PlayStatueExtraDialogueSound()": {
		"methodName": "PlayStatueExtraDialogueSound",
		"parameters": null
	},
	"QuestManager.PlaySkullExtraDialogueSound()": {
		"methodName": "PlaySkullExtraDialogueSound",
		"parameters": null
	},
	"QuestManager.OnTransition(UnityEngine.GameObject)": {
		"methodName": "__0_OnTransition",
		"parameters": [
			"__0_newParent__param"
		]
	},
	"Dialogue_Wizard_2.Start()": {
		"methodName": "_start",
		"parameters": null
	},
	"MainWorldScript.Start()": {
		"methodName": "_start",
		"parameters": null
	},
	"UdonSharp.Examples.Utilities.TrackingDataFollower.Start()": {
		"methodName": "_start",
		"parameters": null
	},
	"UdonSharp.Examples.Utilities.TrackingDataFollower.LateUpdate()": {
		"methodName": "_lateUpdate",
		"parameters": null
	},
	"Miner28.UdonUtils.Network.NetworkedEventCaller.SendData(uint, uint, uint, VRC.SDK3.Data.DataToken[])": {
		"methodName": "__0_SendData",
		"parameters": [
			"__0_method__param",
			"__0_scriptTarget__param",
			"__0_target__param",
			"__0_data__param"
		]
	},
	"Miner28.UdonUtils.Network.NetworkedEventCaller.ReceiveData(int)": {
		"methodName": "__0_ReceiveData",
		"parameters": [
			"__0_startIndex__param"
		]
	},
	"Miner28.UdonUtils.Network.NetworkedEventCaller.SetupCaller()": {
		"methodName": "SetupCaller",
		"parameters": null
	},
	"Miner28.UdonUtils.Network.NetworkedEventCaller.Start()": {
		"methodName": "_start",
		"parameters": null
	},
	"Miner28.UdonUtils.Network.NetworkedEventCaller.OnPreSerialization()": {
		"methodName": "_onPreSerialization",
		"parameters": null
	},
	"Miner28.UdonUtils.Network.NetworkedEventCaller.OnPostSerialization(VRC.Udon.Common.SerializationResult)": {
		"methodName": "_onPostSerialization",
		"parameters": [
			"onPostSerializationResult"
		]
	},
	"Miner28.UdonUtils.Network.NetworkedEventCaller.OnDeserialization(VRC.Udon.Common.DeserializationResult)": {
		"methodName": "_onDeserialization",
		"parameters": [
			"onDeserializationResult"
		]
	},
	"Miner28.UdonUtils.Network.NetworkedEventCaller.HandleDeserialization(VRC.SDKBase.VRCPlayerApi, byte[])": {
		"methodName": "__0_HandleDeserialization",
		"parameters": [
			"__0_sender__param",
			"__0_dataBuffer__param"
		]
	},
	"Miner28.UdonUtils.Network.NetworkedEventCaller.SendUdonMethod(Miner28.UdonUtils.Network.NetworkInterface, int, VRC.SDKBase.VRCPlayerApi)": {
		"methodName": "__0_SendUdonMethod",
		"parameters": [
			"__1_target__param",
			"__0_methodTarget__param",
			"__1_sender__param"
		]
	},
	"Miner28.UdonUtils.Network.NetworkedEventCaller._PrepareSend(uint, string, uint, VRC.SDK3.Data.DataToken[])": {
		"methodName": "__0__PrepareSend",
		"parameters": [
			"__0_intTarget__param",
			"__1_method__param",
			"__1_scriptTarget__param",
			"__1_data__param"
		]
	},
	"Miner28.UdonUtils.Network.NetworkedEventCaller._SendQueue()": {
		"methodName": "_SendQueue",
		"parameters": null
	},
	"Miner28.UdonUtils.Network.NetworkedEventCaller.SetUdonVariable(string, VRC.SDK3.Data.DataToken)": {
		"methodName": "__0_SetUdonVariable",
		"parameters": [
			"__0_variable__param",
			"__0_token__param"
		]
	},
	"Miner28.UdonUtils.Network.NetworkedEventCaller.Log(object)": {
		"methodName": "__0_Log",
		"parameters": [
			"__0_log__param"
		]
	},
	"Miner28.UdonUtils.Network.NetworkedEventCaller.LogWarning(object)": {
		"methodName": "__0_LogWarning",
		"parameters": [
			"__1_log__param"
		]
	},
	"Miner28.UdonUtils.Network.NetworkedEventCaller.LogError(object)": {
		"methodName": "__0_LogError",
		"parameters": [
			"__2_log__param"
		]
	},
	"old_faucet_interactable.Start()": {
		"methodName": "_start",
		"parameters": null
	},
	"old_faucet_interactable.Interact()": {
		"methodName": "_interact",
		"parameters": null
	},
	"old_faucet_interactable.RequestActivate()": {
		"methodName": "RequestActivate",
		"parameters": null
	},
	"old_faucet_interactable.RequestDeactivate()": {
		"methodName": "RequestDeactivate",
		"parameters": null
	},
	"old_faucet_interactable.On_ActivateRequestReceived(int)": {
		"methodName": "__0_On_ActivateRequestReceived",
		"parameters": [
			"__0_id__param"
		]
	},
	"old_faucet_interactable.On_DeactivateRequestReceived(int)": {
		"methodName": "__0_On_DeactivateRequestReceived",
		"parameters": [
			"__1_id__param"
		]
	},
	"old_faucet_interactable.Activate()": {
		"methodName": "Activate",
		"parameters": null
	},
	"old_faucet_interactable.Deactivate()": {
		"methodName": "Deactivate",
		"parameters": null
	},
	"old_faucet_interactable.Update()": {
		"methodName": "_update",
		"parameters": null
	},
	"old_faucet_interactable.UpdateLiquid()": {
		"methodName": "UpdateLiquid",
		"parameters": null
	},
	"old_faucet_interactable.PlayPouringSound()": {
		"methodName": "PlayPouringSound",
		"parameters": null
	},
	"old_faucet_interactable.StopPouringSound()": {
		"methodName": "StopPouringSound",
		"parameters": null
	},
	"old_faucet_interactable.SetLiquidPoolScale(float)": {
		"methodName": "__0_SetLiquidPoolScale",
		"parameters": [
			"__0_scale__param"
		]
	},
	"magicbook.Start()": {
		"methodName": "_start",
		"parameters": null
	},
	"magicbook.OnPickup()": {
		"methodName": "_onPickup",
		"parameters": null
	},
	"magicbook.OnDrop()": {
		"methodName": "_onDrop",
		"parameters": null
	},
	"magicbook.OnPickupUseDown()": {
		"methodName": "_onPickupUseDown",
		"parameters": null
	},
	"magicbook.OnPickupUseUp()": {
		"methodName": "_onPickupUseUp",
		"parameters": null
	},
	"magicbook.On_Received_SpellBookPickedUp(VRC.SDKBase.VRCPlayerApi, int)": {
		"methodName": "__0_On_Received_SpellBookPickedUp",
		"parameters": [
			"__0_castingPlayer__param",
			"__0_bookId__param"
		]
	},
	"magicbook.On_Received_SpellBookDropped(VRC.SDKBase.VRCPlayerApi, int)": {
		"methodName": "__0_On_Received_SpellBookDropped",
		"parameters": [
			"__1_castingPlayer__param",
			"__1_bookId__param"
		]
	},
	"magicbook.On_Received_SpellBeginFire(VRC.SDKBase.VRCPlayerApi, int)": {
		"methodName": "__0_On_Received_SpellBeginFire",
		"parameters": [
			"__2_castingPlayer__param",
			"__2_bookId__param"
		]
	},
	"magicbook.On_Received_SpellEndFire(VRC.SDKBase.VRCPlayerApi, int)": {
		"methodName": "__0_On_Received_SpellEndFire",
		"parameters": [
			"__3_castingPlayer__param",
			"__3_bookId__param"
		]
	},
	"magicbook.LateUpdate()": {
		"methodName": "_lateUpdate",
		"parameters": null
	},
	"Wizard_NPC.Start()": {
		"methodName": "_start",
		"parameters": null
	},
	"Wizard_NPC.Update()": {
		"methodName": "_update",
		"parameters": null
	},
	"Wizard_NPC.PickRandomTargetPosition()": {
		"methodName": "PickRandomTargetPosition",
		"parameters": null
	},
	"Wizard_NPC.Notify_SetTargetPosition(VRC.SDKBase.VRCPlayerApi, UnityEngine.Vector3, int)": {
		"methodName": "__0_Notify_SetTargetPosition",
		"parameters": [
			"__0_requestingPlayer__param",
			"__0_targetPosition__param",
			"__0_id__param"
		]
	},
	"Wizard_NPC.SetTargetPosition(UnityEngine.Vector3, float)": {
		"methodName": "__0_SetTargetPosition",
		"parameters": [
			"__1_targetPosition__param",
			"__0_targetStopDistance__param"
		]
	},
	"Wizard_NPC.GetHeight()": {
		"methodName": "GetHeight",
		"parameters": null
	},
	"Wizard_NPC.HandleMove(float)": {
		"methodName": "__0_HandleMove",
		"parameters": [
			"__0_delta__param"
		]
	},
	"Wizard_NPC.HandleRotation(float)": {
		"methodName": "__0_HandleRotation",
		"parameters": [
			"__1_delta__param"
		]
	},
	"Wizard_NPC.LookAtLocalPlayer(float)": {
		"methodName": "__0_LookAtLocalPlayer",
		"parameters": [
			"__2_delta__param"
		]
	},
	"Wizard_NPC.UpdateWalkSpeed(float)": {
		"methodName": "__0_UpdateWalkSpeed",
		"parameters": [
			"__3_delta__param"
		]
	},
	"Wizard_NPC.Interact()": {
		"methodName": "_interact",
		"parameters": null
	},
	"Wizard_NPC.OnDialogueEnded()": {
		"methodName": "OnDialogueEnded",
		"parameters": null
	},
	"DialogueManager.Start()": {
		"methodName": "_start",
		"parameters": null
	},
	"DialogueManager.LoadDialogue()": {
		"methodName": "LoadDialogue",
		"parameters": null
	},
	"DialogueManager.StartDialogue()": {
		"methodName": "StartDialogue",
		"parameters": null
	},
	"DialogueManager.ShowDialogue()": {
		"methodName": "ShowDialogue",
		"parameters": null
	},
	"DialogueManager.PlaySound(string)": {
		"methodName": "__0_PlaySound",
		"parameters": [
			"__0_soundName__param"
		]
	},
	"DialogueManager.OnDialogueSelected_1()": {
		"methodName": "OnDialogueSelected_1",
		"parameters": null
	},
	"DialogueManager.OnDialogueSelected_2()": {
		"methodName": "OnDialogueSelected_2",
		"parameters": null
	},
	"DialogueManager.OnDialogueSelected_3()": {
		"methodName": "OnDialogueSelected_3",
		"parameters": null
	},
	"DialogueManager.OnOptionSelected(int)": {
		"methodName": "__0_OnOptionSelected",
		"parameters": [
			"__0_optionIndex__param"
		]
	},
	"DialogueManager.ShowDialogueUI()": {
		"methodName": "ShowDialogueUI",
		"parameters": null
	},
	"DialogueManager.HideDialogueUI()": {
		"methodName": "HideDialogueUI",
		"parameters": null
	},
	"DialogueManager.EndDialogue()": {
		"methodName": "EndDialogue",
		"parameters": null
	},
	"DialogueManager.Interact()": {
		"methodName": "_interact",
		"parameters": null
	},
	"candle_lod.Start()": {
		"methodName": "_start",
		"parameters": null
	},
	"candle_lod.OnEnable()": {
		"methodName": "_onEnable",
		"parameters": null
	},
	"candle_lod.SetDefaultState()": {
		"methodName": "SetDefaultState",
		"parameters": null
	},
	"candle_lod.OnPlayerTriggerEnter(VRC.SDKBase.VRCPlayerApi)": {
		"methodName": "_onPlayerTriggerEnter",
		"parameters": [
			"onPlayerTriggerEnterPlayer"
		]
	},
	"candle_lod.OnPlayerTriggerExit(VRC.SDKBase.VRCPlayerApi)": {
		"methodName": "_onPlayerTriggerExit",
		"parameters": [
			"onPlayerTriggerExitPlayer"
		]
	},
	"UdonSharp.Examples.Utilities.BoneFollower.Start()": {
		"methodName": "_start",
		"parameters": null
	},
	"UdonSharp.Examples.Utilities.BoneFollower.Update()": {
		"methodName": "_update",
		"parameters": null
	},
	"HeadlessSkeletonTrigger1.Start()": {
		"methodName": "_start",
		"parameters": null
	},
	"HeadlessSkeletonTrigger1.OnPlayerTriggerEnter(VRC.SDKBase.VRCPlayerApi)": {
		"methodName": "_onPlayerTriggerEnter",
		"parameters": [
			"onPlayerTriggerEnterPlayer"
		]
	},
	"book_mpb.Start()": {
		"methodName": "_start",
		"parameters": null
	},
	"book_mpb.OnValidate()": {
		"methodName": "OnValidate",
		"parameters": null
	},
	"book_mpb.ApplyUVOffset()": {
		"methodName": "ApplyUVOffset",
		"parameters": null
	},
	"SkeletonSpellBall.Start()": {
		"methodName": "_start",
		"parameters": null
	},
	"SkeletonSpellBall.Update()": {
		"methodName": "_update",
		"parameters": null
	},
	"SkeletonSpellBall.On_Explode(bool)": {
		"methodName": "__0_On_Explode",
		"parameters": [
			"__0_didHit__param"
		]
	},
	"blessedwater.Start()": {
		"methodName": "_start",
		"parameters": null
	},
	"blessedwater.OnTriggerEnter(UnityEngine.Collider)": {
		"methodName": "_onTriggerEnter",
		"parameters": [
			"onTriggerEnterOther"
		]
	},
	"Dialogue_Wizard_4.Start()": {
		"methodName": "_start",
		"parameters": null
	},
	"SkullReturnQuestTrigger.Start()": {
		"methodName": "_start",
		"parameters": null
	},
	"SkullReturnQuestTrigger.OnTriggerEnter(UnityEngine.Collider)": {
		"methodName": "_onTriggerEnter",
		"parameters": [
			"onTriggerEnterOther"
		]
	},
	"Skeleton_NPC_Script_Part1.Start()": {
		"methodName": "_start",
		"parameters": null
	},
	"Dialogue_Wizard_3.Start()": {
		"methodName": "_start",
		"parameters": null
	},
	"Dialogue_Wizard_Jail1.Start()": {
		"methodName": "_start",
		"parameters": null
	},
	"UdonSharp.Examples.Utilities.InteractToggle.Interact()": {
		"methodName": "_interact",
		"parameters": null
	},
	"UdonSharp.Examples.Utilities.GlobalToggleObject.Start()": {
		"methodName": "_start",
		"parameters": null
	},
	"UdonSharp.Examples.Utilities.GlobalToggleObject.OnDeserialization()": {
		"methodName": "_onDeserialization",
		"parameters": null
	},
	"UdonSharp.Examples.Utilities.GlobalToggleObject.Interact()": {
		"methodName": "_interact",
		"parameters": null
	},
	"Dialogue_Wizard_1.Start()": {
		"methodName": "_start",
		"parameters": null
	},
	"OcclusionTrigger.Start()": {
		"methodName": "_start",
		"parameters": null
	},
	"OcclusionTrigger.OnEnable()": {
		"methodName": "_onEnable",
		"parameters": null
	},
	"OcclusionTrigger.SetDefaultState()": {
		"methodName": "SetDefaultState",
		"parameters": null
	},
	"OcclusionTrigger.ActivateOccludees()": {
		"methodName": "ActivateOccludees",
		"parameters": null
	},
	"OcclusionTrigger.DeactivateOccludees()": {
		"methodName": "DeactivateOccludees",
		"parameters": null
	},
	"OcclusionTrigger.OnPlayerTriggerEnter(VRC.SDKBase.VRCPlayerApi)": {
		"methodName": "_onPlayerTriggerEnter",
		"parameters": [
			"onPlayerTriggerEnterPlayer"
		]
	},
	"OcclusionTrigger.OnPlayerTriggerExit(VRC.SDKBase.VRCPlayerApi)": {
		"methodName": "_onPlayerTriggerExit",
		"parameters": [
			"onPlayerTriggerExitPlayer"
		]
	},
	"UdonSharp.Examples.Utilities.PlayerModSetter.Start()": {
		"methodName": "_start",
		"parameters": null
	},
	"UdonSharp.Examples.Utilities.WorldAudioSettings.OnPlayerJoined(VRC.SDKBase.VRCPlayerApi)": {
		"methodName": "_onPlayerJoined",
		"parameters": [
			"onPlayerJoinedPlayer"
		]
	},
	"wine_tankard_interactable.Start()": {
		"methodName": "_start",
		"parameters": null
	},
	"wine_tankard_interactable.OnTriggerEnter(UnityEngine.Collider)": {
		"methodName": "_onTriggerEnter",
		"parameters": [
			"onTriggerEnterOther"
		]
	},
	"wine_tankard_interactable.On_RefillRequestReceived(int)": {
		"methodName": "__0_On_RefillRequestReceived",
		"parameters": [
			"__0_id__param"
		]
	},
	"wine_tankard_interactable.OnPickupUseDown()": {
		"methodName": "_onPickupUseDown",
		"parameters": null
	},
	"wine_tankard_interactable.On_DrinkRequestReceived(int, float)": {
		"methodName": "__0_On_DrinkRequestReceived",
		"parameters": [
			"__1_id__param",
			"__0_nextFillLevel__param"
		]
	},
	"wine_tankard_interactable.UpdateLiquidLevel()": {
		"methodName": "UpdateLiquidLevel",
		"parameters": null
	},
	"wine_tankard_interactable.PlaySwallowSound()": {
		"methodName": "PlaySwallowSound",
		"parameters": null
	},
	"wine_tankard_interactable.PlayPouringSound()": {
		"methodName": "PlayPouringSound",
		"parameters": null
	}
}